opsparser/OpenSeesParser.py
opsparser/__about__.py
opsparser/__init__.py
opsparser/enhanced_opensees.py
opsparser/enhanced_opensees.pyi
opsparser/_ide_support/__init__.py
opsparser/_ide_support/analysis.pyi
opsparser/_ide_support/basic.pyi
opsparser/_ide_support/elements.pyi
opsparser/_ide_support/geometry.pyi
opsparser/_ide_support/loads.pyi
opsparser/_ide_support/ndmaterials.pyi
opsparser/_ide_support/uniaxialmaterials.pyi
opsparser/_ide_support/utilities.pyi
opsparser/_manager/_AnalysisManager.py
opsparser/_manager/_BaseHandler.py
opsparser/_manager/_BeamIntegrationManager.py
opsparser/_manager/_BlockManager.py
opsparser/_manager/_ConstraintManager.py
opsparser/_manager/_ElementManager.py
opsparser/_manager/_FrictionModelManager.py
opsparser/_manager/_GeomTransfManager.py
opsparser/_manager/_LoadManager.py
opsparser/_manager/_MaterialManager.py
opsparser/_manager/_NodeManager.py
opsparser/_manager/_RayleighManager.py
opsparser/_manager/_RecorderManager.py
opsparser/_manager/_RegionManager.py
opsparser/_manager/_SectionManager.py
opsparser/_manager/_TimeSeriesManager.py
opsparser/_manager/_UtilityManager.py
opsparser/_manager/__init__.py
opsparser/_manager/_Elements/_BeamColumnHandler.py
opsparser/_manager/_Elements/_BearingHandler.py
opsparser/_manager/_Elements/_BrickHandler.py
opsparser/_manager/_Elements/_CableHandler.py
opsparser/_manager/_Elements/_ContactHandler.py
opsparser/_manager/_Elements/_JointHandler.py
opsparser/_manager/_Elements/_LinkHandler.py
opsparser/_manager/_Elements/_MiscHandler.py
opsparser/_manager/_Elements/_OtherUpHandler.py
opsparser/_manager/_Elements/_PFEMHandler.py
opsparser/_manager/_Elements/_QuadrilateralHandler.py
opsparser/_manager/_Elements/_TetrahedronHandler.py
opsparser/_manager/_Elements/_TriangularHandler.py
opsparser/_manager/_Elements/_TrussHandler.py
opsparser/_manager/_Elements/_UCSDUpHandler.py
opsparser/_manager/_Elements/_ZeroLengthHandler.py
opsparser/_manager/_Elements/__init__.py
opsparser-0.1.3.dist-info/licenses/LICENSE
opsparser-0.1.3.dist-info/METADATA
opsparser-0.1.3.dist-info/WHEEL
opsparser-0.1.3.dist-info/top_level.txt
opsparser-0.1.3.dist-info/RECORD
