Metadata-Version: 2.4
Name: opsparser
Version: 0.1.3
Summary: A lightweight, pure Python implementation of an OpenSeesPy command monitoring tool for capturing, recording, and analyzing OpenSees command execution processes. No third-party dependencies, compatible with all OpenSeesPy versions, with no impact on original performance. Provides flexible API interfaces, supporting custom data processing and event triggering mechanisms.
Requires-Python: >=3.12
License-File: LICENSE
Requires-Dist: openseespy>=3.7.1.2
Dynamic: license-file
